cognitive_twin/__init__.py
cognitive_twin/_compat.py
cognitive_twin/framework/__init__.py
cognitive_twin/framework/config.py
cognitive_twin/framework/feedback.py
cognitive_twin/framework/global_signature.py
cognitive_twin/framework/hybrid_trainer.py
cognitive_twin/framework/multi_source.py
cognitive_twin/framework/pattern_memory.py
cognitive_twin/framework/prompt_generator.py
cognitive_twin/framework/reasoning_encoder.py
cognitive_twin/framework/style_projector.py
cognitive_twin/framework/trainer.py
cognitive_twin/framework/twin.py
cognitive_twin/v3/__init__.py
cognitive_twin/v3/pipeline.py
cognitive_twin/v3/schema.py
cognitive_twin/v3/api/__init__.py
cognitive_twin/v3/api/openai_client.py
cognitive_twin/v3/corpus_surgery/__init__.py
cognitive_twin/v3/corpus_surgery/classifier.py
cognitive_twin/v3/corpus_surgery/constants.py
cognitive_twin/v3/corpus_surgery/functiongemma_scorer.py
cognitive_twin/v3/corpus_surgery/pipeline.py
cognitive_twin/v3/corpus_surgery/quarantine.py
cognitive_twin/v3/corpus_surgery/rewriter.py
cognitive_twin/v3/corpus_surgery/types.py
cognitive_twin/v3/dataset/__init__.py
cognitive_twin/v3/dataset/exporter.py
cognitive_twin/v3/dataset/labeler.py
cognitive_twin/v3/dataset/pair_generator.py
cognitive_twin/v3/eval/__init__.py
cognitive_twin/v3/eval/pipeline.py
cognitive_twin/v3/eval/reporter.py
cognitive_twin/v3/eval/runner.py
cognitive_twin/v3/eval/scorers.py
cognitive_twin/v3/eval/suite.py
cognitive_twin/v3/eval/test_cases.py
cognitive_twin/v3/eval/types.py
cognitive_twin/v3/generators/__init__.py
cognitive_twin/v3/generators/batch_generator.py
cognitive_twin/v3/generators/dpo_factory.py
cognitive_twin/v3/generators/v2_generator.py
cognitive_twin/v3/ingest/__init__.py
cognitive_twin/v3/ingest/claude_json.py
cognitive_twin/v3/ingest/deduplicator.py
cognitive_twin/v3/ingest/normalizer.py
cognitive_twin/v3/ingest/openai_json.py
cognitive_twin/v3/ingest/prompt_logger.py
cognitive_twin/v3/ingest/supabase_extractor.py
cognitive_twin-3.0.0.dist-info/METADATA
cognitive_twin-3.0.0.dist-info/WHEEL
cognitive_twin-3.0.0.dist-info/RECORD
