Metadata-Version: 2.4
Name: cognitive-twin
Version: 3.0.0
Summary: User pattern learning with trajectory-aware DPO training
Project-URL: Homepage, https://github.com/mohameddiomande/cognitive-twin
Project-URL: Documentation, https://github.com/mohameddiomande/cognitive-twin#readme
Project-URL: Repository, https://github.com/mohameddiomande/cognitive-twin
Author: Mohamed Diomande
License-Expression: MIT
Keywords: cognitive-twin,dpo,machine-learning,nlp,trajectory-learning,user-modeling
Classifier: Development Status :: 4 - Beta
Classifier: Intended Audience :: Developers
Classifier: Intended Audience :: Science/Research
Classifier: License :: OSI Approved :: MIT License
Classifier: Programming Language :: Python :: 3
Classifier: Programming Language :: Python :: 3.10
Classifier: Programming Language :: Python :: 3.11
Classifier: Programming Language :: Python :: 3.12
Classifier: Topic :: Scientific/Engineering :: Artificial Intelligence
Requires-Python: >=3.10
Requires-Dist: anthropic>=0.18.0
Requires-Dist: httpx>=0.24.0
Requires-Dist: openai>=1.0.0
Requires-Dist: pydantic>=2.0.0
Requires-Dist: tenacity>=8.0.0
Requires-Dist: tqdm>=4.65.0
Provides-Extra: all
Requires-Dist: accelerate>=0.24.0; extra == 'all'
Requires-Dist: bitsandbytes>=0.41.0; extra == 'all'
Requires-Dist: datasets>=2.14.0; extra == 'all'
Requires-Dist: mypy>=1.0.0; extra == 'all'
Requires-Dist: peft>=0.6.0; extra == 'all'
Requires-Dist: pytest-asyncio>=0.21.0; extra == 'all'
Requires-Dist: pytest>=7.0.0; extra == 'all'
Requires-Dist: rag-plusplus>=1.0.0; extra == 'all'
Requires-Dist: ruff>=0.1.0; extra == 'all'
Requires-Dist: torch>=2.0.0; extra == 'all'
Requires-Dist: transformers>=4.35.0; extra == 'all'
Provides-Extra: dev
Requires-Dist: mypy>=1.0.0; extra == 'dev'
Requires-Dist: pytest-asyncio>=0.21.0; extra == 'dev'
Requires-Dist: pytest>=7.0.0; extra == 'dev'
Requires-Dist: ruff>=0.1.0; extra == 'dev'
Provides-Extra: ragpp
Requires-Dist: rag-plusplus>=1.0.0; extra == 'ragpp'
Provides-Extra: training
Requires-Dist: accelerate>=0.24.0; extra == 'training'
Requires-Dist: bitsandbytes>=0.41.0; extra == 'training'
Requires-Dist: datasets>=2.14.0; extra == 'training'
Requires-Dist: peft>=0.6.0; extra == 'training'
Requires-Dist: torch>=2.0.0; extra == 'training'
Requires-Dist: transformers>=4.35.0; extra == 'training'
